mutwo/isis_converters/__init__.py
mutwo/isis_converters/configurations.py
mutwo/isis_converters/isis.py
mutwo/isis_converters/constants/XSAMPA.py
mutwo/isis_converters/constants/__init__.py
mutwo.ext_isis-0.7.0.dist-info/LICENSE
mutwo.ext_isis-0.7.0.dist-info/METADATA
mutwo.ext_isis-0.7.0.dist-info/WHEEL
mutwo.ext_isis-0.7.0.dist-info/top_level.txt
mutwo.ext_isis-0.7.0.dist-info/RECORD
