Metadata-Version: 2.1
Name: mutwo.ext-isis
Version: 0.7.0
Summary: ISiS extension for event based framework for generative art
Home-page: https://github.com/mutwo-org/mutwo.ext-isis
Author: Levin Eric Zimmermann
Author-email: levin.eric.zimmermann@posteo.eu
License: GPL
Project-URL: Documentation, https://mutwo.readthedocs.io/en/latest/
Platform: UNKNOWN
Requires-Python: >=3.9, <4
License-File: LICENSE
Requires-Dist: mutwo.ext-core (<1.0.0,>=0.55.0)
Requires-Dist: mutwo.ext-music (<1.0.0,>=0.7.0)
Provides-Extra: testing
Requires-Dist: nose ; extra == 'testing'
Requires-Dist: coveralls ; extra == 'testing'
